pyfuncmonitor/__init__.py
pyfuncmonitor/config.py
pyfuncmonitor/core.py
pyfuncmonitor/logging_utils.py
pyfuncmonitor/models.py
pyfuncmonitor-0.1.2.dist-info/WHEEL
pyfuncmonitor-0.1.2.dist-info/METADATA
pyfuncmonitor-0.1.2.dist-info/RECORD
