Metadata-Version: 2.3
Name: pyfuncmonitor
Version: 0.1.2
Summary: A Python decorator for comprehensive function monitoring with execution timing, memory usage tracking, CPU monitoring, input/output validation, and structured logging.
Requires-Dist: psutil>=7.0.0
Requires-Dist: pydantic>=2.11.7
Requires-Dist: pytest>=8.4.1
Requires-Dist: structlog>=25.4.0
Requires-Python: >=3.11
